MANIFEST.in
README.rst
setup.py
shyml.py
shyml.egg-info/PKG-INFO
shyml.egg-info/SOURCES.txt
shyml.egg-info/dependency_links.txt
shyml.egg-info/entry_points.txt
shyml.egg-info/requires.txt
shyml.egg-info/top_level.txt