Metadata-Version: 2.1
Name: shyml
Version: 1.0.1
Summary: write shell in sh.yml
Home-page: https://yourlabs.io/oss/shyml
License: UNKNOWN
Keywords: automation cli
Platform: UNKNOWN
Classifier: Development Status :: 3 - Alpha
Classifier: Environment :: Console
Classifier: Environment :: Plugins
Classifier: Intended Audience :: System Administrators
Classifier: License :: OSI Approved :: MIT License
Classifier: Operating System :: OS Independent
Classifier: Programming Language :: Python :: 3 :: Only
Classifier: Topic :: Database
Classifier: Topic :: Software Development
Classifier: Topic :: System
Classifier: Topic :: Terminals
Requires-Python: >=3
Provides-Extra: test
